oxen_engine/__init__.py
oxen_engine/oxen_engine.cpython-312-darwin.so
oxen_orm-0.2.0.dist-info/METADATA
oxen_orm-0.2.0.dist-info/WHEEL
oxen_orm-0.2.0.dist-info/entry_points.txt
oxen_orm-0.2.0.dist-info/licenses/LICENSE.txt
oxen_orm-0.2.0.dist-info/RECORD
