Metadata-Version: 2.4
Name: oxen-orm
Version: 0.2.0
Requires-Dist: pydantic>=2.0.0
Requires-Dist: typing-extensions>=4.0.0
Requires-Dist: click>=8.0.0
Requires-Dist: pytest>=7.0.0 ; extra == 'dev'
Requires-Dist: pytest-asyncio>=0.24.0 ; extra == 'dev'
Requires-Dist: pytest-cov>=4.0.0 ; extra == 'dev'
Requires-Dist: mypy>=1.0.0 ; extra == 'dev'
Requires-Dist: ruff>=0.1.0 ; extra == 'dev'
Requires-Dist: black>=23.0.0 ; extra == 'dev'
Requires-Dist: asyncpg>=0.28.0 ; extra == 'postgres'
Requires-Dist: aiomysql>=0.2.0 ; extra == 'mysql'
Requires-Dist: aiosqlite>=0.19.0 ; extra == 'sqlite'
Requires-Dist: uvloop>=0.19.0 ; extra == 'performance'
Requires-Dist: aiohttp>=3.8.0 ; extra == 'admin'
Requires-Dist: psutil>=5.9.0 ; extra == 'monitoring'
Provides-Extra: dev
Provides-Extra: postgres
Provides-Extra: mysql
Provides-Extra: sqlite
Provides-Extra: performance
Provides-Extra: admin
Provides-Extra: monitoring
License-File: LICENSE.txt
Summary: High-performance Python ORM backed by Rust - 15× faster than SQLAlchemy with advanced features
Keywords: sql,mysql,postgres,sqlite,relational,database,rdbms,orm,object mapper,async,asyncio,rust,high-performance,window-functions,cte,migrations,admin-interface
Author-email: OxenORM Team <team@oxenorm.dev>
License: MIT
Requires-Python: >=3.9
Project-URL: homepage, https://github.com/Diman2003/OxenORM
Project-URL: repository, https://github.com/Diman2003/OxenORM.git
Project-URL: documentation, https://docs.oxenorm.dev
Project-URL: issues, https://github.com/Diman2003/OxenORM/issues
Project-URL: discussions, https://github.com/Diman2003/OxenORM/discussions
